alu_controller.sv
`include "opcode.vh"

module alu_controller (
    input  logic [1:0] alu_op,
    input  logic [2:0] func3,
    input  logic [6:0] func7,
    output logic [3:0] alu_operation
);

    always_comb begin
        case (alu_op)
            2'b00: alu_operation = 4'b0010; // Load/Store uses ADD
            2'b01: alu_operation = 4'b0110; // Branch uses SUB
            2'b10, 2'b11: begin // R-type and I-type
                case (func3)
                    `FNC_ADD_SUB: begin
                        if (alu_op == 2'b10 && func7 == `FNC7_1)
                            alu_operation = 4'b0110; // SUB
                        else
                            alu_operation = 4'b0010; // ADD
                    end
                    `FNC_SLL: alu_operation = 4'b0100;
                    `FNC_SLT: alu_operation = 4'b1000;
                    `FNC_SLTU: alu_operation = 4'b1001;
                    `FNC_XOR: alu_operation = 4'b0011;
                    `FNC_SRL_SRA: begin
                        if (func7 == `FNC7_1)
                            alu_operation = 4'b0111; // SRA
                        else
                            alu_operation = 4'b0101; // SRL
                    end
                    `FNC_OR:  alu_operation = 4'b0001;
                    `FNC_AND: alu_operation = 4'b0000;
                    default:  alu_operation = 4'b0000;
                endcase
            end
            default: alu_operation = 4'b0000;
        endcase
    end
endmodule

tests/tb_alu_controller.sv
`include "opcode.vh"

module tb_alu_controller;
    logic [1:0] alu_op;
    logic [2:0] func3;
    logic [6:0] func7;
    logic [3:0] alu_operation;

    alu_controller dut(
        .alu_op(alu_op),
        .func3(func3),
        .func7(func7),
        .alu_operation(alu_operation)
    );

    initial begin
        alu_op = 2'b00; func3 = 3'b000; func7 = 7'b0000000; #1;
        if (alu_operation !== 4'b0010) $fatal("Load/store ADD mapping failed");

        alu_op = 2'b01; func3 = 3'b000; func7 = 7'b0000000; #1;
        if (alu_operation !== 4'b0110) $fatal("Branch SUB mapping failed");

        alu_op = 2'b10; func3 = `FNC_ADD_SUB; func7 = `FNC7_0; #1;
        if (alu_operation !== 4'b0010) $fatal("R-type ADD mapping failed");

        func7 = `FNC7_1; #1;
        if (alu_operation !== 4'b0110) $fatal("R-type SUB mapping failed");

        func3 = `FNC_SLL; func7 = `FNC7_0; #1; if (alu_operation !== 4'b0100) $fatal("SLL mapping failed");
        func3 = `FNC_SLT; #1; if (alu_operation !== 4'b1000) $fatal("SLT mapping failed");
        func3 = `FNC_SLTU; #1; if (alu_operation !== 4'b1001) $fatal("SLTU mapping failed");
        func3 = `FNC_XOR;  #1; if (alu_operation !== 4'b0011) $fatal("XOR mapping failed");
        func3 = `FNC_SRL_SRA; func7 = `FNC7_0; #1; if (alu_operation !== 4'b0101) $fatal("SRL mapping failed");
        func7 = `FNC7_1; #1; if (alu_operation !== 4'b0111) $fatal("SRA mapping failed");
        func3 = `FNC_OR;  func7 = `FNC7_0; #1; if (alu_operation !== 4'b0001) $fatal("OR mapping failed");
        func3 = `FNC_AND; #1; if (alu_operation !== 4'b0000) $fatal("AND mapping failed");

        $display("\033[0;32mtb_alu_controller PASS\033[0m");
        $finish;
    end
endmodule

sim_dir/Vtb_alu_controller.vcd
$version Generated by VerilatedVcd $end
$timescale 1ps $end
 $scope module TOP $end
  $scope module tb_alu_controller $end
   $var wire 2 " alu_op [1:0] $end
   $var wire 3 # func3 [2:0] $end
   $var wire 7 $ func7 [6:0] $end
   $var wire 4 % alu_operation [3:0] $end
   $scope module dut $end
    $var wire 2 " alu_op [1:0] $end
    $var wire 3 # func3 [2:0] $end
    $var wire 7 $ func7 [6:0] $end
    $var wire 4 % alu_operation [3:0] $end
   $upscope $end
  $upscope $end
 $upscope $end
$enddefinitions $end


#0
b00 "
b000 #
b0000000 $
b0010 %
#1
b01 "
b0110 %
#2
b10 "
b0010 %
#3
b0100000 $
b0110 %
#4
b001 #
b0000000 $
b0100 %
#5
b010 #
b1000 %
#6
b011 #
b1001 %
#7
b100 #
b0011 %
#8
b101 #
b0101 %
#9
b0100000 $
b0111 %
#10
b110 #
b0000000 $
b0001 %
#11
b111 #
b0000 %
